reusable_utils/__init__.py
reusable_utils/path_utils.py
reusable_utils-0.1.1.dist-info/LICENSE
reusable_utils-0.1.1.dist-info/METADATA
reusable_utils-0.1.1.dist-info/WHEEL
reusable_utils-0.1.1.dist-info/RECORD
