Metadata-Version: 2.3
Name: reusable-utils
Version: 0.1.1
Summary: A collection of reusable utility functions for Python projects.
License: MIT
Keywords: utilities,python,reusable
Author: Julio-M-Siqueira
Author-email: juliomartins1996@gmail.com
Requires-Python: >=3.11
Classifier: Programming Language :: Python :: 3
Classifier: Programming Language :: Python :: 3.11
Classifier: License :: OSI Approved :: MIT License
Classifier: Operating System :: OS Independent
